crcutil/__init__.py
crcutil/__main__.py
crcutil/config/log_config.yaml
crcutil/core/__init__.py
crcutil/core/checksum.py
crcutil/core/checksum_manager.py
crcutil/core/keyboard_monitor.py
crcutil/core/keyboard_monitor_factory.py
crcutil/core/keyboard_monitor_wayland.py
crcutil/core/keyboard_monitor_windows.py
crcutil/core/keyboard_monitor_x11.py
crcutil/core/prompt.py
crcutil/dto/__init__.py
crcutil/dto/bootstrap_paths_dto.py
crcutil/dto/checksum_dto.py
crcutil/dto/crc_diff_report_dto.py
crcutil/dto/user_instructions_dto.py
crcutil/enums/__init__.py
crcutil/enums/user_request.py
crcutil/exception/__init__.py
crcutil/exception/bootstrap_error.py
crcutil/exception/corrupt_crc_error.py
crcutil/exception/device_error.py
crcutil/exception/unexpected_argument_error.py
crcutil/exception/user_error.py
crcutil/serializer/__init__.py
crcutil/serializer/checksum_serializer.py
crcutil/serializer/crc_diff_report_serializer.py
crcutil/util/__init__.py
crcutil/util/crcutil_logger.py
crcutil/util/file_importer.py
crcutil/util/path_ops.py
crcutil/util/static.py
crcutil-2.1.2.dist-info/licenses/LICENSE
crcutil-2.1.2.dist-info/METADATA
crcutil-2.1.2.dist-info/WHEEL
crcutil-2.1.2.dist-info/entry_points.txt
crcutil-2.1.2.dist-info/top_level.txt
crcutil-2.1.2.dist-info/RECORD
