Metadata-Version: 2.4
Name: crcutil
Version: 2.1.2
Author-email: Carlos Florez <carlos@florez.co.uk>
Maintainer-email: Carlos Florez <carlos@florez.co.uk>
License: MIT License
Project-URL: Repository, https://github.com/florez-carlos/crcutil
Classifier: Development Status :: 5 - Production/Stable
Classifier: Programming Language :: Python :: 3.12
Classifier: Programming Language :: Python :: 3.11
Requires-Python: >=3.11
License-File: LICENSE
Requires-Dist: alive-progress==3.3.0
Requires-Dist: pyyaml==6.0.3
Requires-Dist: toml==0.10.2
Requires-Dist: pywin32==311; sys_platform == "win32"
Requires-Dist: jsonschema==4.25.1
Requires-Dist: colorlog==6.10.1
Requires-Dist: pynput==1.8.1
Requires-Dist: python-xlib==0.33
Requires-Dist: evdev==1.9.2; sys_platform == "linux"
Dynamic: license-file
